django_comment_migrate/__init__.py
django_comment_migrate/apps.py
django_comment_migrate/config.py
django_comment_migrate/db_comments.py
django_comment_migrate/utils.py
django_comment_migrate/backends/__init__.py
django_comment_migrate/backends/base.py
django_comment_migrate/backends/mssql.py
django_comment_migrate/backends/mysql.py
django_comment_migrate/backends/postgresql.py
django_comment_migrate/management/__init__.py
django_comment_migrate/management/commands/__init__.py
django_comment_migrate/management/commands/migratecomment.py
django_comment_migrate-0.1.7.dist-info/LICENSE
django_comment_migrate-0.1.7.dist-info/METADATA
django_comment_migrate-0.1.7.dist-info/WHEEL
django_comment_migrate-0.1.7.dist-info/top_level.txt
django_comment_migrate-0.1.7.dist-info/RECORD
