Metadata-Version: 2.1
Name: django-comment-migrate
Version: 0.1.7
Summary: An app that provides Django model comment migration 
Home-page: https://github.com/starryrbs/django-comment-migrate.git
Author: starryrbs
Author-email: 1322096624@qq.com
License: MIT
Keywords: django-comment-migrate
Classifier: Programming Language :: Python :: 3.6
Classifier: Programming Language :: Python :: 3.7
Classifier: Programming Language :: Python :: 3.8
Requires-Python: >=3.6
License-File: LICENSE
